aeolus/__init__.py
aeolus/__main__.py
aeolus/_version.py
aeolus/cli.py
aeolus/coord.py
aeolus/core.py
aeolus/decor.py
aeolus/exceptions.py
aeolus/io.py
aeolus/lfric.py
aeolus/log.py
aeolus/meta.py
aeolus/postprocess.py
aeolus/proc_um_output.py
aeolus/region.py
aeolus/runtime.py
aeolus/subset.py
aeolus/synthobs.py
aeolus/calc/__init__.py
aeolus/calc/calculus.py
aeolus/calc/diag.py
aeolus/calc/flux_h.py
aeolus/calc/metpy.py
aeolus/calc/stats.py
aeolus/calc/tl.py
aeolus/const/__init__.py
aeolus/const/const.py
aeolus/const/store/earth.json
aeolus/const/store/general.json
aeolus/const/store/proxb.json
aeolus/const/store/titan.json
aeolus/const/store/trap1d.json
aeolus/const/store/trap1e.json
aeolus/const/store/trap1f.json
aeolus/model/__init__.py
aeolus/model/base.py
aeolus/model/lfric.py
aeolus/model/um.py
aeolus/plot/__init__.py
aeolus/plot/cart.py
aeolus/plot/cloud.py
aeolus/plot/cm_custom.py
aeolus/plot/mpl.py
aeolus/plot/pv.py
aeolus/plot/text.py
aeolus-24.11.1.2.dist-info/LICENSE
aeolus-24.11.1.2.dist-info/METADATA
aeolus-24.11.1.2.dist-info/WHEEL
aeolus-24.11.1.2.dist-info/entry_points.txt
aeolus-24.11.1.2.dist-info/top_level.txt
aeolus-24.11.1.2.dist-info/RECORD
