Metadata-Version: 2.1
Name: aeolus
Version: 24.11.1.2
Summary: Analysis and visualisation of atmospheric model output powered by iris
Author-email: Aeolus Contributors <dennis.sergeev@gmail.com>
License: GNU LESSER GENERAL PUBLIC LICENSE
Project-URL: Code, https://github.com/exoclim/aeolus
Project-URL: Issues, https://github.com/exoclim/aeolus/issues
Project-URL: Discussions, https://github.com/exoclim/aeolus/discussions
Project-URL: Documentation, https://exoclim.github.io/aeolus
Keywords: atmospheric-science,climate-model,earth-science,planetary-science
Classifier: Development Status :: 1 - Planning
Classifier: Intended Audience :: Science/Research
Classifier: License :: OSI Approved :: BSD License
Classifier: Natural Language :: English
Classifier: Operating System :: OS Independent
Classifier: Programming Language :: Python :: 3 :: Only
Classifier: Programming Language :: Python :: 3.10
Classifier: Programming Language :: Python :: 3.11
Classifier: Programming Language :: Python :: 3.12
Classifier: Topic :: Scientific/Engineering :: Atmospheric Science
Requires-Python: >=3.10
License-File: LICENSE
Requires-Dist: cached-property>=1.5.1
Requires-Dist: click>=8.1.7
Requires-Dist: click-default-group>=1.2.4
Requires-Dist: matplotlib>=3.6
Requires-Dist: numpy!=1.24.3,>=1.21.0
Requires-Dist: scitools-iris>=3.10
